clock_test/clock_check.v
module clock_check;
  
  reg clk30M = 1'b0;
  reg nrst;
  //30Mhz is 0.3ns in one period
  always #150 clk30M <= ~clk30M;
  wire tx=1'b1;
  wire clk_puls;
  reg [11:0] clkdiv = 12'b0;
  always @(posedge clk30M & nrst) 
	  clkdiv <= clkdiv+12'd1; 	
  always @(!nrst)
	  clkdiv <= 12'b0;
  assign clk_puls  = clkdiv[11:0]==12'd3125;
  always @(posedge clk30M & nrst)
	  if(clk_puls==1)
		  clkdiv <= 12'd0;
 
  initial
  begin
	nrst=0;
	#600;
	nrst =1;
    #150110000;
	nrst=0;
	#20;
    //$finish();
  end
  initial 
  begin 
    $dumpfile("dump.vcd");
    $dumpvars(0);
  end
  
endmodule

clock_test/asdf/dump.vcd
$date
	Thu Jul 21 13:09:24 2022
$end
$version
	ModelSim Version 2020.3
$end
$timescale
	1ps
$end

$scope module clock_check $end
$var reg 1 ! clk30M $end
$var reg 1 " nrst $end
$var wire 1 # tx $end
$var wire 1 $ clk_puls $end
$var reg 12 % clkdiv [11:0] $end
$upscope $end
$enddefinitions $end
#0
$dumpvars
0!
0"
b0 %
1#
0$
$end
#150
1!
#300
0!
#450
1!
#600
1"
0!
b1 %
b0 %
#750
1!
b1 %
#900
0!
#1050
1!
b10 %
#1200
0!
#1350
1!
b11 %
#1500
0!
#1650
1!
b100 %
#1800
0!
#1950
1!
b101 %
#2100
0!
#2250
1!
b110 %
#2400
0!
#2550
1!
b111 %
#2700
0!
#2850
1!
b1000 %
#3000
0!
#3150
1!
b1001 %
#3300
0!
#3450
1!
b1010 %
#3600
0!
#3750
1!
b1011 %
#3900
0!
#4050
1!
b1100 %
#4200
0!
#4350
1!
b1101 %
#4500
0!
#4650
1!
b1110 %
#4800
0!
#4950
1!
b1111 %
#5100
0!
#5250
1!
b10000 %
#5400
0!
#5550
1!
b10001 %
#5700
0!
#5850
1!
b10010 %
#6000
0!
#6150
1!
b10011 %
#6300
0!
#6450
1!
b10100 %
#6600
0!
#6750
1!
b10101 %
#6900
0!
#7050
1!
b10110 %
#7200
0!
#7350
1!
b10111 %
#7500
0!
#7650
1!
b11000 %
#7800
0!
#7950
1!
b11001 %
#8100
0!
#8250
1!
b11010 %
#8400
0!
#8550
1!
b11011 %
#8700
0!
#8850
1!
b11100 %
#9000
0!
#9150
1!
b11101 %
#9300
0!
#9450
1!
b11110 %
#9600
0!
#9750
1!
b11111 %
#9900
0!
#10050
1!
b100000 %
#10200
0!
#10350
1!
b100001 %
#10500
0!
#10650
1!
b100010 %
#10800
0!
#10950
1!
b100011 %
#11100
0!
#11250
1!
b100100 %
#11400
0!
#11550
1!
b100101 %
#11700
0!
#11850
1!
b100110 %
#12000
0!
#12150
1!
b100111 %
#12300
0!
#12450
1!
b101000 %
#12600
0!
#12750
1!
b101001 %
#12900
0!
#13050
1!
b101010 %
#13200
0!
#13350
1!
b101011 %
#13500
0!
#13650
1!
b101100 %
#13800
0!
#13950
1!
b101101 %
#14100
0!
#14250
1!
b101110 %
#14400
0!
#14550
1!
b101111 %
#14700
0!
#14850
1!
b110000 %
#15000
0!
#15150
1!
b110001 %
#15300
0!
#15450
1!
b110010 %
#15600
0!
#15750
1!
b110011 %
#15900
0!
#16050
1!
b110100 %
#16200
0!
#16350
1!
b110101 %
#16500
0!
#16650
1!
b110110 %
#16800
0!
#16950
1!
b110111 %
#17100
0!
#17250
1!
b111000 %
#17400
0!
#17550
1!
b111001 %
#17700
0!
#17850
1!
b111010 %
#18000
0!
#18150
1!
b111011 %
#18300
0!
#18450
1!
b111100 %
#18600
0!
#18750
1!
b111101 %
#18900
0!
#19050
1!
b111110 %
#19200
0!
#19350
1!
b111111 %
#19500
0!
#19650
1!
b1000000 %
#19800
0!
#19950
1!
b1000001 %
#20100
0!
#20250
1!
b1000010 %
#20400
0!
#20550
1!
b1000011 %
#20700
0!
#20850
1!
b1000100 %
#21000
0!
#21150
1!
b1000101 %
#21300
0!
#21450
1!
b1000110 %
#21600
0!
#21750
1!
b1000111 %
#21900
0!
#22050
1!
b1001000 %
#22200
0!
#22350
1!
b1001001 %
#22500
0!
#22650
1!
b1001010 %
#22800
0!
#22950
1!
b1001011 %
#23100
0!
#23250
1!
b1001100 %
#23400
0!
#23550
1!
b1001101 %
#23700
0!
#23850
1!
b1001110 %
#24000
0!
#24150
1!
b1001111 %
#24300
0!
#24450
1!
b1010000 %
#24600
0!
#24750
1!
b1010001 %
#24900
0!
#25050
1!
b1010010 %
#25200
0!
#25350
1!
b1010011 %
#25500
0!
#25650
1!
b1010100 %
#25800
0!
#25950
1!
b1010101 %
#26100
0!
#26250
1!
b1010110 %
#26400
0!
#26550
1!
b1010111 %
#26700
0!
#26850
1!
b1011000 %
#27000
0!
#27150
1!
b1011001 %
#27300
0!
#27450
1!
b1011010 %
#27600
0!
#27750
1!
b1011011 %
#27900
0!
#28050
1!
b1011100 %
#28200
0!
#28350
1!
b1011101 %
#28500
0!
#28650
1!
b1011110 %
#28800
0!
#28950
1!
b1011111 %
#29100
0!
#29250
1!
b1100000 %
#29400
0!
#29550
1!
b1100001 %
#29700
0!
#29850
1!
b1100010 %
#30000
0!
#30150
1!
b1100011 %
#30300
0!
#30450
1!
b1100100 %
#30600
0!
#30750
1!
b1100101 %
#30900
0!
#31050
1!
b1100110 %
#31200
0!
#31350
1!
b1100111 %
#31500
0!
#31650
1!
b1101000 %
#31800
0!
#31950
1!
b1101001 %
#32100
0!
#32250
1!
b1101010 %
#32400
0!
#32550
1!
b1101011 %
#32700
0!
#32850
1!
b1101100 %
#33000
0!
#33150
1!
b1101101 %
#33300
0!
#33450
1!
b1101110 %
#33600
0!
#33750
1!
b1101111 %
#33900
0!
#34050
1!
b1110000 %
#34200
0!
#34350
1!
b1110001 %
#34500
0!
#34650
1!
b1110010 %
#34800
0!
#34950
1!
b1110011 %
#35100
0!
#35250
1!
b1110100 %
#35400
0!
#35550
1!
b1110101 %
#35700
0!
#35850
1!
b1110110 %
#36000
0!
#36150
1!
b1110111 %
#36300
0!
#36450
1!
b1111000 %
#36600
0!
#36750
1!
b1111001 %
#36900
0!
#37050
1!
b1111010 %
#37200
0!
#37350
1!
b1111011 %
#37500
0!
#37650
1!
b1111100 %
#37800
0!
#37950
1!
b1111101 %
#38100
0!
#38250
1!
b1111110 %
#38400
0!
#38550
1!
b1111111 %
#38700
0!
#38850
1!
b10000000 %
#39000
0!
#39150
1!
b10000001 %
#39300
0!
#39450
1!
b10000010 %
#39600
0!
#39750
1!
b10000011 %
#39900
0!
#40050
1!
b10000100 %
#40200
0!
#40350
1!
b10000101 %
#40500
0!
#40650
1!
b10000110 %
#40800
0!
#40950
1!
b10000111 %
#41100
0!
#41250
1!
b10001000 %
#41400
0!
#41550
1!
b10001001 %
#41700
0!
#41850
1!
b10001010 %
#42000
0!
#42150
1!
b10001011 %
#42300
0!
#42450
1!
b10001100 %
#42600
0!
#42750
1!
b10001101 %
#42900
0!
#43050
1!
b10001110 %
#43200
0!
#43350
1!
b10001111 %
#43500
0!
#43650
1!
b10010000 %
#43800
0!
#43950
1!
b10010001 %
#44100
0!
#44250
1!
b10010010 %
#44400
0!
#44550
1!
b10010011 %
#44700
0!
#44850
1!
b10010100 %
#45000
0!
#45150
1!
b10010101 %
#45300
0!
#45450
1!
b10010110 %
#45600
0!
#45750
1!
b10010111 %
#45900
0!
#46050
1!
b10011000 %
#46200
0!
#46350
1!
b10011001 %
#46500
0!
#46650
1!
b10011010 %
#46800
0!
#46950
1!
b10011011 %
#47100
0!
#47250
1!
b10011100 %
#47400
0!
#47550
1!
b10011101 %
#47700
0!
#47850
1!
b10011110 %
#48000
0!
#48150
1!
b10011111 %
#48300
0!
#48450
1!
b10100000 %
#48600
0!
#48750
1!
b10100001 %
#48900
0!
#49050
1!
b10100010 %
#49200
0!
#49350
1!
b10100011 %
#49500
0!
#49650
1!
b10100100 %
#49800
0!
#49950
1!
b10100101 %
#50100
0!
#50250
1!
b10100110 %
#50400
0!
#50550
1!
b10100111 %
#50700
0!
#50850
1!
b10101000 %
#51000
0!
#51150
1!
b10101001 %
#51300
0!
#51450
1!
b10101010 %
#51600
0!
#51750
1!
b10101011 %
#51900
0!
#52050
1!
b10101100 %
#52200
0!
#52350
1!
b10101101 %
#52500
0!
#52650
1!
b10101110 %
#52800
0!
#52950
1!
b10101111 %
#53100
0!
#53250
1!
b10110000 %
#53400
0!
#53550
1!
b10110001 %
#53700
0!
#53850
1!
b10110010 %
#54000
0!
#54150
1!
b10110011 %
#54300
0!
#54450
1!
b10110100 %
#54600
0!
#54750
1!
b10110101 %
#54900
0!
#55050
1!
b10110110 %
#55200
0!
#55350
1!
b10110111 %
#55500
0!
#55650
1!
b10111000 %
#55800
0!
#55950
1!
b10111001 %
#56100
0!
#56250
1!
b10111010 %
#56400
0!
#56550
1!
b10111011 %
#56700
0!
#56850
1!
b10111100 %
#57000
0!
#57150
1!
b10111101 %
#57300
0!
#57450
1!
b10111110 %
#57600
0!
#57750
1!
b10111111 %
#57900
0!
#58050
1!
b11000000 %
#58200
0!
#58350
1!
b11000001 %
#58500
0!
#58650
1!
b11000010 %
#58800
0!
#58950
1!
b11000011 %
#59100
0!
#59250
1!
b11000100 %
#59400
0!
#59550
1!
b11000101 %
#59700
0!
#59850
1!
b11000110 %
#60000
0!
#60150
1!
b11000111 %
#60300
0!
#60450
1!
b11001000 %
#60600
0!
#60750
1!
b11001001 %
#60900
0!
#61050
1!
b11001010 %
#61200
0!
#61350
1!
b11001011 %
#61500
0!
#61650
1!
b11001100 %
#61800
0!
#61950
1!
b11001101 %
#62100
0!
#62250
1!
b11001110 %
#62400
0!
#62550
1!
b11001111 %
#62700
0!
#62850
1!
b11010000 %
#63000
0!
#63150
1!
b11010001 %
#63300
0!
#63450
1!
b11010010 %
#63600
0!
#63750
1!
b11010011 %
#63900
0!
#64050
1!
b11010100 %
#64200
0!
#64350
1!
b11010101 %
#64500
0!
#64650
1!
b11010110 %
#64800
0!
#64950
1!
b11010111 %
#65100
0!
#65250
1!
b11011000 %
#65400
0!
#65550
1!
b11011001 %
#65700
0!
#65850
1!
b11011010 %
#66000
0!
#66150
1!
b11011011 %
#66300
0!
#66450
1!
b11011100 %
#66600
0!
#66750
1!
b11011101 %
#66900
0!
#67050
1!
b11011110 %
#67200
0!
#67350
1!
b11011111 %
#67500
0!
#67650
1!
b11100000 %
#67800
0!
#67950
1!
b11100001 %
#68100
0!
#68250
1!
b11100010 %
#68400
0!
#68550
1!
b11100011 %
#68700
0!
#68850
1!
b11100100 %
#69000
0!
#69150
1!
b11100101 %
#69300
0!
#69450
1!
b11100110 %
#69600
0!
#69750
1!
b11100111 %
#69900
0!
#70050
1!
b11101000 %
#70200
0!
#70350
1!
b11101001 %
#70500
0!
#70650
1!
b11101010 %
#70800
0!
#70950
1!
b11101011 %
#71100
0!
#71250
1!
b11101100 %
#71400
0!
#71550
1!
b11101101 %
#71700
0!
#71850
1!
b11101110 %
#72000
0!
#72150
1!
b11101111 %
#72300
0!
#72450
1!
b11110000 %
#72600
0!
#72750
1!
b11110001 %
#72900
0!
#73050
1!
b11110010 %
#73200
0!
#73350
1!
b11110011 %
#73500
0!
#73650
1!
b11110100 %
#73800
0!
#73950
1!
b11110101 %
#74100
0!
#74250
1!
b11110110 %
#74400
0!
#74550
1!
b11110111 %
#74700
0!
#74850
1!
b11111000 %
#75000
0!
#75150
1!
b11111001 %
#75300
0!
#75450
1!
b11111010 %
#75600
0!
#75750
1!
b11111011 %
#75900
0!
#76050
1!
b11111100 %
#76200
0!
#76350
1!
b11111101 %
#76500
0!
#76650
1!
b11111110 %
#76800
0!
#76950
1!
b11111111 %
#77100
0!
#77250
1!
b100000000 %
#77400
0!
#77550
1!
b100000001 %
#77700
0!
#77850
1!
b100000010 %
#78000
0!
#78150
1!
b100000011 %
#78300
0!
#78450
1!
b100000100 %
#78600
0!
#78750
1!
b100000101 %
#78900
0!
#79050
1!
b100000110 %
#79200
0!
#79350
1!
b100000111 %
#79500
0!
#79650
1!
b100001000 %
#79800
0!
#79950
1!
b100001001 %
#80100
0!
#80250
1!
b100001010 %
#80400
0!
#80550
1!
b100001011 %
#80700
0!
#80850
1!
b100001100 %
#81000
0!
#81150
1!
b100001101 %
#81300
0!
#81450
1!
b100001110 %
#81600
0!
#81750
1!
b100001111 %
#81900
0!
#82050
1!
b100010000 %
#82200
0!
#82350
1!
b100010001 %
#82500
0!
#82650
1!
b100010010 %
#82800
0!
#82950
1!
b100010011 %
#83100
0!
#83250
1!
b100010100 %
#83400
0!
#83550
1!
b100010101 %
#83700
0!
#83850
1!
b100010110 %
#84000
0!
#84150
1!
b100010111 %
#84300
0!
#84450
1!
b100011000 %
#84600
0!
#84750
1!
b100011001 %
#84900
0!
#85050
1!
b100011010 %
#85200
0!
#85350
1!
b100011011 %
#85500
0!
#85650
1!
b100011100 %
#85800
0!
#85950
1!
b100011101 %
#86100
0!
#86250
1!
b100011110 %
#86400
0!
#86550
1!
b100011111 %
#86700
0!
#86850
1!
b100100000 %
#87000
0!
#87150
1!
b100100001 %
#87300
0!
#87450
1!
b100100010 %
#87600
0!
#87750
1!
b100100011 %
#87900
0!
#88050
1!
b100100100 %
#88200
0!
#88350
1!
b100100101 %
#88500
0!
#88650
1!
b100100110 %
#88800
0!
#88950
1!
b100100111 %
#89100
0!
#89250
1!
b100101000 %
#89400
0!
#89550
1!
b100101001 %
#89700
0!
#89850
1!
b100101010 %
#90000
0!
#90150
1!
b100101011 %
#90300
0!
#90450
1!
b100101100 %
#90600
0!
#90750
1!
b100101101 %
#90900
0!
#91050
1!
b100101110 %
#91200
0!
#91350
1!
b100101111 %
#91500
0!
#91650
1!
b100110000 %
#91800
0!
#91950
1!
b100110001 %
#92100
0!
#92250
1!
b100110010 %
#92400
0!
#92550
1!
b100110011 %
#92700
0!
#92850
1!
b100110100 %
#93000
0!
#93150
1!
b100110101 %
#93300
0!
#93450
1!
b100110110 %
#93600
0!
#93750
1!
b100110111 %
#93900
0!
#94050
1!
b100111000 %
#94200
0!
#94350
1!
b100111001 %
#94500
0!
#94650
1!
b100111010 %
#94800
0!
#94950
1!
b100111011 %
#95100
0!
#95250
1!
b100111100 %
#95400
0!
#95550
1!
b100111101 %
#95700
0!
#95850
1!
b100111110 %
#96000
0!
#96150
1!
b100111111 %
#96300
0!
#96450
1!
b101000000 %
#96600
0!
#96750
1!
b101000001 %
#96900
0!
#97050
1!
b101000010 %
#97200
0!
#97350
1!
b101000011 %
#97500
0!
#97650
1!
b101000100 %
#97800
0!
#97950
1!
b101000101 %
#98100
0!
#98250
1!
b101000110 %
#98400
0!
#98550
1!
b101000111 %
#98700
0!
#98850
1!
b101001000 %
#99000
0!
#99150
1!
b101001001 %
#99300
0!
#99450
1!
b101001010 %
#99600
0!
#99750
1!
b101001011 %
#99900
0!
#100050
1!
b101001100 %
#100200
0!
#100350
1!
b101001101 %
#100500
0!
#100650
1!
b101001110 %
#100800
0!
#100950
1!
b101001111 %
#101100
0!
#101250
1!
b101010000 %
#101400
0!
#101550
1!
b101010001 %
#101700
0!
#101850
1!
b101010010 %
#102000
0!
#102150
1!
b101010011 %
#102300
0!
#102450
1!
b101010100 %
#102600
0!
#102750
1!
b101010101 %
#102900
0!
#103050
1!
b101010110 %
#103200
0!
#103350
1!
b101010111 %
#103500
0!
#103650
1!
b101011000 %
#103800
0!
#103950
1!
b101011001 %
#104100
0!
#104250
1!
b101011010 %
#104400
0!
#104550
1!
b101011011 %
#104700
0!
#104850
1!
b101011100 %
#105000
0!
#105150
1!
b101011101 %
#105300
0!
#105450
1!
b101011110 %
#105600
0!
#105750
1!
b101011111 %
#105900
0!
#106050
1!
b101100000 %
#106200
0!
#106350
1!
b101100001 %
#106500
0!
#106650
1!
b101100010 %
#106800
0!
#106950
1!
b101100011 %
#107100
0!
#107250
1!
b101100100 %
#107400
0!
#107550
1!
b101100101 %
#107700
0!
#107850
1!
b101100110 %
#108000
0!
#108150
1!
b101100111 %
#108300
0!
#108450
1!
b101101000 %
#108600
0!
#108750
1!
b101101001 %
#108900
0!
#109050
1!
b101101010 %
#109200
0!
#109350
1!
b101101011 %
#109500
0!
#109650
1!
b101101100 %
#109800
0!
#109950
1!
b101101101 %
#110100
0!
#110250
1!
b101101110 %
#110400
0!
#110550
1!
b101101111 %
#110700
0!
#110850
1!
b101110000 %
#111000
0!
#111150
1!
b101110001 %
#111300
0!
#111450
1!
b101110010 %
#111600
0!
#111750
1!
b101110011 %
#111900
0!
#112050
1!
b101110100 %
#112200
0!
#112350
1!
b101110101 %
#112500
0!
#112650
1!
b101110110 %
#112800
0!
#112950
1!
b101110111 %
#113100
0!
#113250
1!
b101111000 %
#113400
0!
#113550
1!
b101111001 %
#113700
0!
#113850
1!
b101111010 %
#114000
0!
#114150
1!
b101111011 %
#114300
0!
#114450
1!
b101111100 %
#114600
0!
#114750
1!
b101111101 %
#114900
0!
#115050
1!
b101111110 %
#115200
0!
#115350
1!
b101111111 %
#115500
0!
#115650
1!
b110000000 %
#115800
0!
#115950
1!
b110000001 %
#116100
0!
#116250
1!
b110000010 %
#116400
0!
#116550
1!
b110000011 %
#116700
0!
#116850
1!
b110000100 %
#117000
0!
#117150
1!
b110000101 %
#117300
0!
#117450
1!
b110000110 %
#117600
0!
#117750
1!
b110000111 %
#117900
0!
#118050
1!
b110001000 %
#118200
0!
#118350
1!
b110001001 %
#118500
0!
#118650
1!
b110001010 %
#118800
0!
#118950
1!
b110001011 %
#119100
0!
#119250
1!
b110001100 %
#119400
0!
#119550
1!
b110001101 %
#119700
0!
#119850
1!
b110001110 %
#120000
0!
#120150
1!
b110001111 %
#120300
0!
#120450
1!
b110010000 %
#120600
0!
#120750
1!
b110010001 %
#120900
0!
#121050
1!
b110010010 %
#121200
0!
#121350
1!
b110010011 %
#121500
0!
#121650
1!
b110010100 %
#121800
0!
#121950
1!
b110010101 %
#122100
0!
#122250
1!
b110010110 %
#122400
0!
#122550
1!
b110010111 %
#122700
0!
#122850
1!
b110011000 %
#123000
0!
#123150
1!
b110011001 %
#123300
0!
#123450
1!
b110011010 %
#123600
0!
#123750
1!
b110011011 %
#123900
0!
#124050
1!
b110011100 %
#124200
0!
#124350
1!
b110011101 %
#124500
0!
#124650
1!
b110011110 %
#124800
0!
#124950
1!
b110011111 %
#125100
0!
#125250
1!
b110100000 %
#125400
0!
#125550
1!
b110100001 %
#125700
0!
#125850
1!
b110100010 %
#126000
0!
#126150
1!
b110100011 %
#126300
0!
#126450
1!
b110100100 %
#126600
0!
#126750
1!
b110100101 %
#126900
0!
#127050
1!
b110100110 %
#127200
0!
#127350
1!
b110100111 %
#127500
0!
#127650
1!
b110101000 %
#127800
0!
#127950
1!
b110101001 %
#128100
0!
#128250
1!
b110101010 %
#128400
0!
#128550
1!
b110101011 %
#128700
0!
#128850
1!
b110101100 %
#129000
0!
#129150
1!
b110101101 %
#129300
0!
#129450
1!
b110101110 %
#129600
0!
#129750
1!
b110101111 %
#129900
0!
#130050
1!
b110110000 %
#130200
0!
#130350
1!
b110110001 %
#130500
0!
#130650
1!
b110110010 %
#130800
0!
#130950
1!
b110110011 %
#131100
0!
#131250
1!
b110110100 %
#131400
0!
#131550
1!
b110110101 %
#131700
0!
#131850
1!
b110110110 %
#132000
0!
#132150
1!
b110110111 %
#132300
0!
#132450
1!
b110111000 %
#132600
0!
#132750
1!
b110111001 %
#132900
0!
#133050
1!
b110111010 %
#133200
0!
#133350
1!
b110111011 %
#133500
0!
#133650
1!
b110111100 %
#133800
0!
#133950
1!
b110111101 %
#134100
0!
#134250
1!
b110111110 %
#134400
0!
#134550
1!
b110111111 %
#134700
0!
#134850
1!
b111000000 %
#135000
0!
#135150
1!
b111000001 %
#135300
0!
#135450
1!
b111000010 %
#135600
0!
#135750
1!
b111000011 %
#135900
0!
#136050
1!
b111000100 %
#136200
0!
#136350
1!
b111000101 %
#136500
0!
#136650
1!
b111000110 %
#136800
0!
#136950
1!
b111000111 %
#137100
0!
#137250
1!
b111001000 %
#137400
0!
#137550
1!
b111001001 %
#137700
0!
#137850
1!
b111001010 %
#138000
0!
#138150
1!
b111001011 %
#138300
0!
#138450
1!
b111001100 %
#138600
0!
#138750
1!
b111001101 %
#138900
0!
#139050
1!
b111001110 %
#139200
0!
#139350
1!
b111001111 %
#139500
0!
#139650
1!
b111010000 %
#139800
0!
#139950
1!
b111010001 %
#140100
0!
#140250
1!
b111010010 %
#140400
0!
#140550
1!
b111010011 %
#140700
0!
#140850
1!
b111010100 %
#141000
0!
#141150
1!
b111010101 %
#141300
0!
#141450
1!
b111010110 %
#141600
0!
#141750
1!
b111010111 %
#141900
0!
#142050
1!
b111011000 %
#142200
0!
#142350
1!
b111011001 %
#142500
0!
#142650
1!
b111011010 %
#142800
0!
#142950
1!
b111011011 %
#143100
0!
#143250
1!
b111011100 %
#143400
0!
#143550
1!
b111011101 %
#143700
0!
#143850
1!
b111011110 %
#144000
0!
#144150
1!
b111011111 %
#144300
0!
#144450
1!
b111100000 %
#144600
0!
#144750
1!
b111100001 %
#144900
0!
#145050
1!
b111100010 %
#145200
0!
#145350
1!
b111100011 %
#145500
0!
#145650
1!
b111100100 %
#145800
0!
#145950
1!
b111100101 %
#146100
0!
#146250
1!
b111100110 %
#146400
0!
#146550
1!
b111100111 %
#146700
0!
#146850
1!
b111101000 %
#147000
0!
#147150
1!
b111101001 %
#147300
0!
#147450
1!
b111101010 %
#147600
0!
#147750
1!
b111101011 %
#147900
0!
#148050
1!
b111101100 %
#148200
0!
#148350
1!
b111101101 %
#148500
0!
#148650
1!
b111101110 %
#148800
0!
#148950
1!
b111101111 %
#149100
0!
#149250
1!
b111110000 %
#149400
0!
#149550
1!
b111110001 %
#149700
0!
#149850
1!
b111110010 %
#150000
0!
#150150
1!
b111110011 %
#150300
0!
#150450
1!
b111110100 %
#150600
0!
#150750
1!
b111110101 %
#150900
0!
#151050
1!
b111110110 %
#151200
0!
#151350
1!
b111110111 %
#151500
0!
#151650
1!
b111111000 %
#151800
0!
#151950
1!
b111111001 %
#152100
0!
#152250
1!
b111111010 %
#152400
0!
#152550
1!
b111111011 %
#152700
0!
#152850
1!
b111111100 %
#153000
0!
#153150
1!
b111111101 %
#153300
0!
#153450
1!
b111111110 %
#153600
0!
#153750
1!
b111111111 %
#153900
0!
#154050
1!
b1000000000 %
#154200
0!
#154350
1!
b1000000001 %
#154500
0!
#154650
1!
b1000000010 %
#154800
0!
#154950
1!
b1000000011 %
#155100
0!
#155250
1!
b1000000100 %
#155400
0!
#155550
1!
b1000000101 %
#155700
0!
#155850
1!
b1000000110 %
#156000
0!
#156150
1!
b1000000111 %
#156300
0!
#156450
1!
b1000001000 %
#156600
0!
#156750
1!
b1000001001 %
#156900
0!
#157050
1!
b1000001010 %
#157200
0!
#157350
1!
b1000001011 %
#157500
0!
#157650
1!
b1000001100 %
#157800
0!
#157950
1!
b1000001101 %
#158100
0!
#158250
1!
b1000001110 %
#158400
0!
#158550
1!
b1000001111 %
#158700
0!
#158850
1!
b1000010000 %
#159000
0!
#159150
1!
b1000010001 %
#159300
0!
#159450
1!
b1000010010 %
#159600
0!
#159750
1!
b1000010011 %
#159900
0!
#160050
1!
b1000010100 %
#160200
0!
#160350
1!
b1000010101 %
#160500
0!
#160650
1!
b1000010110 %
#160800
0!
#160950
1!
b1000010111 %
#161100
0!
#161250
1!
b1000011000 %
#161400
0!
#161550
1!
b1000011001 %
#161700
0!
#161850
1!
b1000011010 %
#162000
0!
#162150
1!
b1000011011 %
#162300
0!
#162450
1!
b1000011100 %
#162600
0!
#162750
1!
b1000011101 %
#162900
0!
#163050
1!
b1000011110 %
#163200
0!
#163350
1!
b1000011111 %
#163500
0!
#163650
1!
b1000100000 %
#163800
0!
#163950
1!
b1000100001 %
#164100
0!
#164250
1!
b1000100010 %
#164400
0!
#164550
1!
b1000100011 %
#164700
0!
#164850
1!
b1000100100 %
#165000
0!
#165150
1!
b1000100101 %
#165300
0!
#165450
1!
b1000100110 %
#165600
0!
#165750
1!
b1000100111 %
#165900
0!
#166050
1!
b1000101000 %
#166200
0!
#166350
1!
b1000101001 %
#166500
0!
#166650
1!
b1000101010 %
#166800
0!
#166950
1!
b1000101011 %
#167100
0!
#167250
1!
b1000101100 %
#167400
0!
#167550
1!
b1000101101 %
#167700
0!
#167850
1!
b1000101110 %
#168000
0!
#168150
1!
b1000101111 %
#168300
0!
#168450
1!
b1000110000 %
#168600
0!
#168750
1!
b1000110001 %
#168900
0!
#169050
1!
b1000110010 %
#169200
0!
#169350
1!
b1000110011 %
#169500
0!
#169650
1!
b1000110100 %
#169800
0!
#169950
1!
b1000110101 %
#170100
0!
#170250
1!
b1000110110 %
#170400
0!
#170550
1!
b1000110111 %
#170700
0!
#170850
1!
b1000111000 %
#171000
0!
#171150
1!
b1000111001 %
#171300
0!
#171450
1!
b1000111010 %
#171600
0!
#171750
1!
b1000111011 %
#171900
0!
#172050
1!
b1000111100 %
#172200
0!
#172350
1!
b1000111101 %
#172500
0!
#172650
1!
b1000111110 %
#172800
0!
#172950
1!
b1000111111 %
#173100
0!
#173250
1!
b1001000000 %
#173400
0!
#173550
1!
b1001000001 %
#173700
0!
#173850
1!
b1001000010 %
#174000
0!
#174150
1!
b1001000011 %
#174300
0!
#174450
1!
b1001000100 %
#174600
0!
#174750
1!
b1001000101 %
#174900
0!
#175050
1!
b1001000110 %
#175200
0!
#175350
1!
b1001000111 %
#175500
0!
#175650
1!
b1001001000 %
#175800
0!
#175950
1!
b1001001001 %
#176100
0!
#176250
1!
b1001001010 %
#176400
0!
#176550
1!
b1001001011 %
#176700
0!
#176850
1!
b1001001100 %
#177000
0!
#177150
1!
b1001001101 %
#177300
0!
#177450
1!
b1001001110 %
#177600
0!
#177750
1!
b1001001111 %
#177900
0!
#178050
1!
b1001010000 %
#178200
0!
#178350
1!
b1001010001 %
#178500
0!
#178650
1!
b1001010010 %
#178800
0!
#178950
1!
b1001010011 %
#179100
0!
#179250
1!
b1001010100 %
#179400
0!
#179550
1!
b1001010101 %
#179700
0!
#179850
1!
b1001010110 %
#180000
0!
#180150
1!
b1001010111 %
#180300
0!
#180450
1!
b1001011000 %
#180600
0!
#180750
1!
b1001011001 %
#180900
0!
#181050
1!
b1001011010 %
#181200
0!
#181350
1!
b1001011011 %
#181500
0!
#181650
1!
b1001011100 %
#181800
0!
#181950
1!
b1001011101 %
#182100
0!
#182250
1!
b1001011110 %
#182400
0!
#182550
1!
b1001011111 %
#182700
0!
#182850
1!
b1001100000 %
#183000
0!
#183150
1!
b1001100001 %
#183300
0!
#183450
1!
b1001100010 %
#183600
0!
#183750
1!
b1001100011 %
#183900
0!
#184050
1!
b1001100100 %
#184200
0!
#184350
1!
b1001100101 %
#184500
0!
#184650
1!
b1001100110 %
#184800
0!
#184950
1!
b1001100111 %
#185100
0!
#185250
1!
b1001101000 %
#185400
0!
#185550
1!
b1001101001 %
#185700
0!
#185850
1!
b1001101010 %
#186000
0!
#186150
1!
b1001101011 %
#186300
0!
#186450
1!
b1001101100 %
#186600
0!
#186750
1!
b1001101101 %
#186900
0!
#187050
1!
b1001101110 %
#187200
0!
#187350
1!
b1001101111 %
#187500
0!
#187650
1!
b1001110000 %
#187800
0!
#187950
1!
b1001110001 %
#188100
0!
#188250
1!
b1001110010 %
#188400
0!
#188550
1!
b1001110011 %
#188700
0!
#188850
1!
b1001110100 %
#189000
0!
#189150
1!
b1001110101 %
#189300
0!
#189450
1!
b1001110110 %
#189600
0!
#189750
1!
b1001110111 %
#189900
0!
#190050
1!
b1001111000 %
#190200
0!
#190350
1!
b1001111001 %
#190500
0!
#190650
1!
b1001111010 %
#190800
0!
#190950
1!
b1001111011 %
#191100
0!
#191250
1!
b1001111100 %
#191400
0!
#191550
1!
b1001111101 %
#191700
0!
#191850
1!
b1001111110 %
#192000
0!
#192150
1!
b1001111111 %
#192300
0!
#192450
1!
b1010000000 %
#192600
0!
#192750
1!
b1010000001 %
#192900
0!
#193050
1!
b1010000010 %
#193200
0!
#193350
1!
b1010000011 %
#193500
0!
#193650
1!
b1010000100 %
#193800
0!
#193950
1!
b1010000101 %
#194100
0!
#194250
1!
b1010000110 %
#194400
0!
#194550
1!
b1010000111 %
#194700
0!
#194850
1!
b1010001000 %
#195000
0!
#195150
1!
b1010001001 %
#195300
0!
#195450
1!
b1010001010 %
#195600
0!
#195750
1!
b1010001011 %
#195900
0!
#196050
1!
b1010001100 %
#196200
0!
#196350
1!
b1010001101 %
#196500
0!
#196650
1!
b1010001110 %
#196800
0!
#196950
1!
b1010001111 %
#197100
0!
#197250
1!
b1010010000 %
#197400
0!
#197550
1!
b1010010001 %
#197700
0!
#197850
1!
b1010010010 %
#198000
0!
#198150
1!
b1010010011 %
#198300
0!
#198450
1!
b1010010100 %
#198600
0!
#198750
1!
b1010010101 %
#198900
0!
#199050
1!
b1010010110 %
#199200
0!
#199350
1!
b1010010111 %
#199500
0!
#199650
1!
b1010011000 %
#199800
0!
#199950
1!
b1010011001 %
#200100
0!
#200250
1!
b1010011010 %
#200400
0!
#200550
1!
b1010011011 %
#200700
0!
#200850
1!
b1010011100 %
#201000
0!
#201150
1!
b1010011101 %
#201300
0!
#201450
1!
b1010011110 %
#201600
0!
#201750
1!
b1010011111 %
#201900
0!
#202050
1!
b1010100000 %
#202200
0!
#202350
1!
b1010100001 %
#202500
0!
#202650
1!
b1010100010 %
#202800
0!
#202950
1!
b1010100011 %
#203100
0!
#203250
1!
b1010100100 %
#203400
0!
#203550
1!
b1010100101 %
#203700
0!
#203850
1!
b1010100110 %
#204000
0!
#204150
1!
b1010100111 %
#204300
0!
#204450
1!
b1010101000 %
#204600
0!
